Workbook

Sheet Ingredient Library
A1: Ingredient Library
A2: Mezcaleria Lupa, Cluj-Napoca · Romania | As of 2026-06-04 | The ONLY place you type costs. Edit a container cost and every recipe + the Menu Summary update automatically.
A3: Currency: | B3: RON
A4: All amounts ex-VAT / wholesale, in the currency above.
A6: Ingredient | B6: Container size | C6: Unit | D6: Container cost | E6: Cost per unit | F6: Estimated? | G6: Note
A7: Don Julio Blanco | B7: 700 | C7: ml | D7: 230 | E7: =IF(N(B7)=0,0,D7/B7) | F7: Yes
A8: Suc de grapefruit roz | B8: 1000 | C8: ml | D8: 14 | E8: =IF(N(B8)=0,0,D8/B8) | F8: Yes
A9: Suc de lime | B9: 1000 | C9: ml | D9: 28 | E9: =IF(N(B9)=0,0,D9/B9) | F9: Yes
A10: Sirop de agave afumat | B10: 500 | C10: ml | D10: 18 | E10: =IF(N(B10)=0,0,D10/B10) | F10: No
A11: Cointreau (non-Diageo) | B11: 700 | C11: ml | D11: 130 | E11: =IF(N(B11)=0,0,D11/B11) | F11: Yes
A12: Absint | B12: 700 | C12: ml | D12: 180 | E12: =IF(N(B12)=0,0,D12/B12) | F12: Yes
A13: Roată grapefruit deshidratată | B13: 1 | C13: each | D13: 1.5 | E13: =IF(N(B13)=0,0,D13/B13) | F13: No
A14: Ramă sare-chili | B14: 1 | C14: each | D14: 0.5 | E14: =IF(N(B14)=0,0,D14/B14) | F14: No
A15: Sirop de agave afumat (homemade) | B15: 500 | C15: ml | D15: 18 | E15: =IF(N(B15)=0,0,D15/B15) | F15: No | G15: Homemade batch — cost per ml = batch cost / batch yield.

Sheet Vatra de Agave
A1: Vatra de Agave
A2: Hero: Don Julio Blanco | Mezcaleria Lupa, Cluj-Napoca · Romania | As of 2026-06-04
A3: Costs pull live from the Ingredient Library — do not type costs here.
A5: Ingredient | B5: Qty | C5: Unit | D5: Cost / unit | E5: Line cost | F5: % of cost
A6: Don Julio Blanco | B6: 40 | C6: ml | D6: ='Ingredient Library'!$E$7 | E6: =N(B6)*1*D6 | F6: =IF(B17=0,0,E6/B17)
A7: Suc de grapefruit roz | B7: 25 | C7: ml | D7: ='Ingredient Library'!$E$8 | E7: =N(B7)*1*D7 | F7: =IF(B17=0,0,E7/B17)
A8: Suc de lime | B8: 15 | C8: ml | D8: ='Ingredient Library'!$E$9 | E8: =N(B8)*1*D8 | F8: =IF(B17=0,0,E8/B17)
A9: Sirop de agave afumat | B9: 12.5 | C9: ml | D9: ='Ingredient Library'!$E$10 | E9: =N(B9)*1*D9 | F9: =IF(B17=0,0,E9/B17)
A10: Cointreau (non-Diageo) | B10: 5 | C10: ml | D10: ='Ingredient Library'!$E$11 | E10: =N(B10)*1*D10 | F10: =IF(B17=0,0,E10/B17)
A11: Absint | B11: 2 | C11: dash | D11: ='Ingredient Library'!$E$12 | E11: =N(B11)*0.9*D11 | F11: =IF(B17=0,0,E11/B17)
A12: Roată grapefruit deshidratată | B12: 1 | C12: each | D12: ='Ingredient Library'!$E$13 | E12: =N(B12)*1*D12 | F12: =IF(B17=0,0,E12/B17)
A13: Ramă sare-chili | B13: 1 | C13: each | D13: ='Ingredient Library'!$E$14 | E13: =N(B13)*1*D13 | F13: =IF(B17=0,0,E13/B17)
A14: Sirop de agave afumat (homemade) | C14: ml | D14: ='Ingredient Library'!$E$15 | E14: =N(B14)*1*D14 | F14: =IF(B17=0,0,E14/B17)
A16: COST & PRICING
A17: Subtotal (ingredient cost) | B17: =SUM(E6:E14)
A18: Buffer % (spillage/waste) | B18: 0.1
A19: Buffer amount | B19: =B17*B18
A20: TOTAL recipe cost | B20: =B17+B19
A21: Target pour cost % | B21: 0.22
A22: Suggested price | B22: =IF(B21=0,0,B20/B21)
A23: Rounded menu price
A24: Actual pour cost % | B24: =IF((IF(N(B23)=0,B22,B23))=0,0,B20/(IF(N(B23)=0,B22,B23)))
A25: Cash gross profit | B25: =(IF(N(B23)=0,B22,B23))-B20
A26: Gross profit % | B26: =1-B24

Sheet Menu Summary
A1: Menu Summary
A2: Mezcaleria Lupa, Cluj-Napoca · Romania | As of 2026-06-04 | All figures pull live from each recipe sheet.
A3: Currency: | B3: ='Ingredient Library'!$B$3
A4: All amounts ex-VAT / wholesale, in the currency above.
A6: Recipe | B6: Total cost | C6: Suggested price | D6: Rounded price | E6: Pour cost % | F6: Cash GP | G6: GP % | H6: Menu class
A7: Vatra de Agave | B7: ='Vatra de Agave'!B20 | C7: ='Vatra de Agave'!B22 | D7: ='Vatra de Agave'!B23 | E7: ='Vatra de Agave'!B24 | F7: ='Vatra de Agave'!B25 | G7: ='Vatra de Agave'!B26
A9: Menu engineering — classify each item by Cash GP (value axis) x Popularity (sales axis):
A10: Star = high Cash GP + high popularity (promote, protect).
A11: Plowhorse = low Cash GP + high popularity (re-engineer cost or price).
A12: Puzzle = high Cash GP + low popularity (reposition / push).
A13: Dog = low Cash GP + low popularity (consider cutting).
